trustML/__init__.py
trustML/computation.py
trustML/configreader.py
trustML/trust.py
trustML/assessment_methods/__init__.py
trustML/assessment_methods/assessmentmethod.py
trustML/assessment_methods/bayesiannetwork.py
trustML/assessment_methods/weightedaverage.py
trustML/metrics/__init__.py
trustML/metrics/accuracy.py
trustML/metrics/avgrobustnessbound.py
trustML/metrics/brierscore.py
trustML/metrics/equalopportunity.py
trustML/metrics/expectedcalibration.py
trustML/metrics/explanationsaccuracyTED.py
trustML/metrics/f1.py
trustML/metrics/faithfulnessLIME.py
trustML/metrics/metric.py
trustML/metrics/monotonicityLIME.py
trustML/metrics/ppercentage.py
trustML/metrics/precision.py
trustML/metrics/recall.py
trustML/metrics/roc.py
trustML/metrics/verifiederrortree.py
trustml-2.6.2.dist-info/LICENSE
trustml-2.6.2.dist-info/WHEEL
trustml-2.6.2.dist-info/METADATA
trustml-2.6.2.dist-info/RECORD
