Metadata-Version: 2.1
Name: trustML
Version: 2.6.2
Summary: Trust for Machine Learning
Author-email: Martí Manzano <marti.manzano@upc.edu>
Requires-Python: >=3.7
Classifier: Programming Language :: Python :: 3
Classifier: License :: OSI Approved :: MIT License
Classifier: Operating System :: OS Independent
Requires-Dist: scikit-learn==0.24.1
Requires-Dist: pandas==1.2.4
Requires-Dist: adversarial-robustness-toolbox==1.8.0
Requires-Dist: numpy==1.19.5
Requires-Dist: scikit-lego==0.6.8
Requires-Dist: aix360==0.1.0
Requires-Dist: uq360==0.1.1
Requires-Dist: anytree==2.8.0
Requires-Dist: requests-oauthlib==1.3.0
Requires-Dist: pyyaml==5.4.1
Requires-Dist: lime==0.2.0.1
Requires-Dist: requests==2.25.1
Requires-Dist: tensorflow==2.6.0
Requires-Dist: scipy==1.6.2
Requires-Dist: pdoc3 ; extra == "doc"
Requires-Dist: matplotlib==3.6.3 ; extra == "doc"
Requires-Dist: dill==0.3.4 ; extra == "doc"
Project-URL: API Documentation, https://martimanzano.github.io/trustML
Project-URL: Bug Tracker, https://github.com/martimanzano/trustML/issues
Project-URL: Homepage, https://github.com/martimanzano/trustML
Project-URL: Wiki, https://github.com/martimanzano/trustML/wiki
Provides-Extra: doc
